xkcd_python/__init__.py
xkcd_python/xkcd.py
xkcd_python-2.9.0.dist-info/LICENSE
xkcd_python-2.9.0.dist-info/WHEEL
xkcd_python-2.9.0.dist-info/METADATA
xkcd_python-2.9.0.dist-info/RECORD
